CONTRIBUTORS
LICENSE
MANIFEST.in
README.md
setup.py
Flask_Track_Usage.egg-info/PKG-INFO
Flask_Track_Usage.egg-info/SOURCES.txt
Flask_Track_Usage.egg-info/dependency_links.txt
Flask_Track_Usage.egg-info/not-zip-safe
Flask_Track_Usage.egg-info/requires.txt
Flask_Track_Usage.egg-info/top_level.txt
alembic/README
alembic/env.py
alembic/script.py.mako
alembic/versions/07c46d368ba4_initial_empty_db.py
alembic/versions/0aedc36acb3f_upgrade_to_2_0_0.py
alembic/versions/ca514840f404_increase_ip_info_size.py
docs/conf.py
docs/hooks.rst
docs/index.rst
docs/_themes/LICENSE
docs/_themes/README
docs/_themes/flask_theme_support.py
docs/_themes/flask/layout.html
docs/_themes/flask/relations.html
docs/_themes/flask/theme.conf
docs/_themes/flask/static/flasky.css_t
docs/_themes/flask/static/small_flask.css
docs/_themes/flask_small/layout.html
docs/_themes/flask_small/theme.conf
docs/_themes/flask_small/static/flasky.css_t
src/flask_track_usage/__init__.py
src/flask_track_usage/storage/__init__.py
src/flask_track_usage/storage/couchdb.py
src/flask_track_usage/storage/mongo.py
src/flask_track_usage/storage/output.py
src/flask_track_usage/storage/printer.py
src/flask_track_usage/storage/redis_db.py
src/flask_track_usage/storage/sql.py
src/flask_track_usage/summarization/__init__.py
src/flask_track_usage/summarization/mongoenginestorage.py
src/flask_track_usage/summarization/sqlstorage.py
test/__init__.py
test/test_blueprints_include_exclude.py
test/test_data.py
test/test_include_exclude.py
test/test_storage_mongo.py
test/test_storage_sqlalchemy.py
test/test_summarize_mongoengine.py
test/test_summarize_sqlalchemy.py