Metadata-Version: 1.1
Name: Flask-Track-Usage
Version: 2.0.0
Summary: Basic metrics tracking for the Flask framework.
Home-page: https://github.com/ashcrow/flask-track-usage
Author: Steve Milner
Author-email: UNKNOWN
License: MBSD
Platform: any
Classifier: Environment :: Web Environment
Classifier: Intended Audience :: Developers
Classifier: License :: OSI Approved :: BSD License
Classifier: Operating System :: OS Independent
Classifier: Programming Language :: Python
Classifier: Topic :: Internet :: WWW/HTTP :: Dynamic Content
Classifier: Topic :: Software Development :: Libraries :: Python Modules
